jsonmason/__init__.py
jsonmason/attrdict.py
jsonmason/cli.py
jsonmason/libjsonmason.py
jsonmason-0.2.0.dist-info/LICENSE
jsonmason-0.2.0.dist-info/METADATA
jsonmason-0.2.0.dist-info/WHEEL
jsonmason-0.2.0.dist-info/entry_points.txt
jsonmason-0.2.0.dist-info/top_level.txt
jsonmason-0.2.0.dist-info/RECORD
