Metadata-Version: 2.1
Name: jsonmason
Version: 0.2.0
Summary: jsonmason - deconstruct JSON into assignments, mangle them at will, and reconstitute JSON from the assignments.
Home-page: https://github.com/blinkingtwelve/jsonmason
Author: nullenenenen
Author-email: nullenenenen@gavagai.eu
License: Unlicense
Project-URL: Documentation, https://github.com/blinkingtwelve/jsonmason/blob/master/README.md
Project-URL: Source, https://github.com/blinkingtwelve/jsonmason
Keywords: json
Classifier: Development Status :: 4 - Beta
Classifier: Environment :: Console
Classifier: Intended Audience :: Developers
Classifier: License :: OSI Approved :: The Unlicense (Unlicense)
Classifier: Operating System :: OS Independent
Classifier: Topic :: Software Development
Classifier: Programming Language :: Python :: 3
Requires-Python: >=3.8
License-File: LICENSE
